README.md
setup.py
sqltrans/__init__.py
sqltrans/exceptions.py
sqltrans/helpers.py
sqltrans/queries.py
sqltrans/search.py
sqltrans/transform.py
sqltrans/translate.py
sqltrans/utils.py
sqltrans.egg-info/PKG-INFO
sqltrans.egg-info/SOURCES.txt
sqltrans.egg-info/dependency_links.txt
sqltrans.egg-info/requires.txt
sqltrans.egg-info/top_level.txt
sqltrans/translations/__init__.py
sqltrans/translations/generic_rules.py
sqltrans/translations/spark_to_redshift.py
sqltrans/translations/utils.py